Metadata-Version: 2.4
Name: notion_python_client
Version: 0.0.2
Summary: This package is a Python client for the Notion API.
Author-email: Marten Jostmann <marten.jostmann@gmail.com>
Project-URL: Homepage, https://github.com/martenjostmann/notion-python-client
Classifier: Programming Language :: Python :: 3
Classifier: License :: OSI Approved :: MIT License
Classifier: Operating System :: OS Independent
Requires-Python: >=3.9
Requires-Dist: pydantic>=2.3.0
Requires-Dist: requests>=2.31.0
